printf/__init__.py
printf/color.py
printf/printf.py
printf_fiachia-2.0.3.dist-info/METADATA
printf_fiachia-2.0.3.dist-info/WHEEL
printf_fiachia-2.0.3.dist-info/licence.txt
printf_fiachia-2.0.3.dist-info/top_level.txt
printf_fiachia-2.0.3.dist-info/RECORD
