Metadata-Version: 2.1
Name: printf-fiachia
Version: 2.0.3
Summary: Easy print() with color
Home-page: UNKNOWN
Author: fiachia
Author-email: 208473302@qq.com
Maintainer: fiachia
Maintainer-email: 208473302@qq.com
License: BSD License
Platform: all
License-File: licence.txt
